{
    "weapon": [
        {
            "type": "weapon",
            "name": "Punch",
            "code": "fist-01",
            "description": "A bloodied fist. The weapon of the desperate and the damned.",
            "slot": "weapon",
            "slotsNumber": 1,
            "requirements": {},
            "range": {
                "maximumX": 1,
                "maximumY": 2
            },
            "damage": [
                {
                    "chance": 65,
                    "crushing": 8,
                    "deviation": 3
                }
            ],
            "useCost": {
                "stamina": 5,
                "actionPoints": 4
            }
        },
        {
            "type": "weapon",
            "name": "Teeth",
            "code": "teeth-01",
            "description": "Gnashing fangs, eager to tear flesh and taste the copper tang of blood. A savage bite in the darkness.",
            "slot": "weapon",
            "slotsNumber": 1,
            "requirements": {},
            "range": {
                "maximumX": 1,
                "maximumY": 2
            },
            "damage": [
                {
                    "chance": 60,
                    "cutting": 8,
                    "deviation": 3
                },
                {
                    "chance": 15,
                    "duration": 3,
                    "bleeding": 2,
                    "deviation": 1
                }
            ],
            "useCost": {
                "stamina": 10,
                "actionPoints": 4
            }
        },
        {
            "type": "weapon",
            "name": "Teeth",
            "code": "teeth-02",
            "description": "A feral lunge from above, jaws snapping with primal hunger. The shriek of prey echoes in the night.",
            "slot": "weapon",
            "slotsNumber": 1,
            "requirements": {},
            "range": {
                "maximumX": 2,
                "maximumY": 2
            },
            "damage": [
                {
                    "chance": 60,
                    "cutting": 8,
                    "deviation": 3
                },
                {
                    "chance": 15,
                    "duration": 3,
                    "bleeding": 2,
                    "deviation": 1
                }
            ],
            "useCost": {
                "stamina": 10,
                "actionPoints": 5
            }
        },
        {
            "type": "weapon",
            "name": "Fire Puch",
            "code": "fire-punch-01",
            "description": "A fist wreathed in searing flame, scorching flesh and soul alike. Pain and fire entwined.",
            "slot": "weapon",
            "slotsNumber": 1,
            "requirements": {},
            "range": {
                "maximumX": 1,
                "maximumY": 2
            },
            "damage": [
                {
                    "chance": 60,
                    "crushing": 8,
                    "fire": 12,
                    "deviation": 3
                },
                {
                    "chance": 15,
                    "duration": 3,
                    "fire": 3,
                    "deviation": 1
                }
            ],
            "useCost": {
                "stamina": 10,
                "actionPoints": 5
            }
        },
        {
            "type": "weapon",
            "name": "Plasma Touch",
            "code": "plasma-touch-01",
            "description": "A touch crackling with eldritch lightning, burning the flesh and soul with unholy energy.",
            "slot": "weapon",
            "slotsNumber": 1,
            "requirements": {},
            "range": {
                "maximumX": 1,
                "maximumY": 2
            },
            "damage": [
                {
                    "chance": 65,
                    "lightning": 17,
                    "deviation": 5
                },
                {
                    "chance": 15,
                    "duration": 3,
                    "lightning": 3,
                    "deviation": 2
                }
            ],
            "useCost": {
                "mana": 10,
                "stamina": 3,
                "actionPoints": 5
            }
        },
        {
            "type": "weapon",
            "name": "Sight",
            "code": "sight-01",
            "description": "A baleful gaze unleashes a spectral projectile, cold and merciless as the grave.",
            "ammunitionKind": "magicCharge",
            "slot": "weapon",
            "slotsNumber": 1,
            "requirements": {},
            "range": {
                "maximumX": 5,
                "maximumY": 5,
                "minimumX": 2
            },
            "damage": [
                {
                    "chance": 60
                }
            ],
            "useCost": {
                "mana": 10,
                "actionPoints": 5
            }
        },
        {
            "type": "weapon",
            "name": "Throat",
            "code": "throat-01",
            "description": "A guttural incantation, spewing forth a cursed missile from the abyss within.",
            "ammunitionKind": "magicCharge",
            "slot": "weapon",
            "slotsNumber": 1,
            "requirements": {},
            "range": {
                "maximumX": 5,
                "maximumY": 5,
                "minimumX": 2
            },
            "damage": [
                {
                    "chance": 70
                }
            ],
            "useCost": {
                "mana": 10,
                "actionPoints": 5
            }
        },
        {
            "type": "weapon",
            "name": "Short Sword",
            "code": "sword-01",
            "description": "A battered blade, its edge dulled by countless battles. Reliable in the hands of the desperate.",
            "slot": "weapon",
            "canBeThrownAway": true,
            "slotsNumber": 1,
            "requirements": {
                "physique": 5
            },
            "range": {
                "maximumX": 1,
                "maximumY": 2
            },
            "damage": [
                {
                    "chance": 65,
                    "cutting": 18,
                    "crushing": 3,
                    "deviation": 2
                },
                {
                    "duration": 3,
                    "chance": 5,
                    "bleeding": 3,
                    "deviation": 1
                }
            ],
            "useCost": {
                "stamina": 10,
                "actionPoints": 4
            }
        },
        {
            "type": "weapon",
            "name": "Short Sword",
            "code": "sword-02",
            "description": "A soldier's trusted blade, its steel whispering tales of blood and betrayal.",
            "durability": 300,
            "slot": "weapon",
            "canBeSold": true,
            "canBeThrownAway": true,
            "slotsNumber": 1,
            "requirements": {
                "physique": 8
            },
            "range": {
                "maximumX": 1,
                "maximumY": 2
            },
            "damage": [
                {
                    "chance": 75,
                    "cutting": 28,
                    "crushing": 5,
                    "deviation": 2
                },
                {
                    "duration": 3,
                    "chance": 15,
                    "bleeding": 3,
                    "deviation": 1
                }
            ],
            "useCost": {
                "stamina": 12,
                "actionPoints": 4
            },
            "price": {
                "coins": 2000
            }
        },
        {
            "type": "weapon",
            "name": "Light Sword",
            "code": "sword-magic-01",
            "description": "A sword crackling with lightning, its blade a beacon of wrath in the storm.",
            "durability": 300,
            "slot": "weapon",
            "canBeSold": true,
            "canBeThrownAway": true,
            "slotsNumber": 1,
            "requirements": {
                "physique": 8,
                "intelligence": 4
            },
            "range": {
                "maximumX": 1,
                "maximumY": 2
            },
            "damage": [
                {
                    "chance": 75,
                    "cutting": 27,
                    "crushing": 5,
                    "lightning": 10,
                    "deviation": 5
                },
                {
                    "duration": 1,
                    "lightning": 3,
                    "deviation": 3
                },
                {
                    "duration": 3,
                    "chance": 15,
                    "bleeding": 3,
                    "deviation": 1
                }
            ],
            "useCost": {
                "stamina": 12,
                "mana": 3
            },
            "price": {
                "coins": 3000,
                "ruby": 10,
                "actionPoints": 5
            }
        },
        {
            "type": "weapon",
            "name": "Spear",
            "code": "spear-01",
            "description": "A long, wicked spear, perfect for keeping foes at bay or impaling them in the mud.",
            "durability": 300,
            "slot": "weapon",
            "canBeSold": true,
            "canBeThrownAway": true,
            "slotsNumber": 2,
            "requirements": {
                "physique": 5
            },
            "range": {
                "maximumX": 2,
                "maximumY": 2
            },
            "damage": [
                {
                    "chance": 75,
                    "stabbing": 27,
                    "deviation": 5
                },
                {
                    "duration": 3,
                    "chance": 15,
                    "bleeding": 4,
                    "deviation": 3
                }
            ],
            "modification": [
                {
                    "damage": {
                        "stabbing": 10
                    }
                }
            ],
            "useCost": {
                "stamina": 10,
                "actionPoints": 5
            },
            "price": {
                "coins": 1500
            }
        },
        {
            "type": "weapon",
            "name": "Bow",
            "code": "bow-01",
            "description": "A weathered bow, its string taut with the promise of silent death from afar.",
            "ammunitionKind": "arrow",
            "slot": "weapon",
            "canBeThrownAway": true,
            "slotsNumber": 2,
            "requirements": {
                "physique": 5
            },
            "range": {
                "maximumX": 5,
                "maximumY": 5,
                "minimumX": 2
            },
            "damage": [
                {
                    "chance": 65
                }
            ],
            "useCost": {
                "stamina": 8,
                "actionPoints": 5
            }
        },
        {
            "type": "weapon",
            "name": "Bow",
            "code": "bow-02",
            "description": "A hunter's bow, its wood darkened by years of use and the blood of quarry.",
            "ammunitionKind": "arrow",
            "durability": 300,
            "slot": "weapon",
            "canBeSold": true,
            "canBeThrownAway": true,
            "slotsNumber": 2,
            "requirements": {
                "physique": 5,
                "agility": 5
            },
            "range": {
                "maximumX": 5,
                "maximumY": 5,
                "minimumX": 2
            },
            "damage": [
                {
                    "chance": 75,
                    "stabbing": 10
                }
            ],
            "useCost": {
                "stamina": 10,
                "actionPoints": 5
            },
            "price": {
                "coins": 1500
            }
        },
        {
            "type": "weapon",
            "name": "Fire Bow",
            "code": "bow-magic-01",
            "description": "A bow imbued with infernal fire, each arrow a burning curse upon its target.",
            "ammunitionKind": "arrow",
            "durability": 300,
            "slot": "weapon",
            "canBeSold": true,
            "canBeThrownAway": true,
            "slotsNumber": 2,
            "requirements": {
                "physique": 5,
                "agility": 8
            },
            "range": {
                "maximumX": 5,
                "maximumY": 5,
                "minimumX": 2
            },
            "damage": [
                {
                    "chance": 75,
                    "stabbing": 10,
                    "fire": 10
                },
                {
                    "duration": 1,
                    "fire": 4,
                    "deviation": 2
                }
            ],
            "useCost": {
                "stamina": 10,
                "actionPoints": 5
            },
            "price": {
                "coins": 2000,
                "ruby": 10
            }
        },
        {
            "type": "weapon",
            "name": "Dagger",
            "code": "dagger-01",
            "description": "A slender blade, perfect for silent murders and quick betrayals in the night.",
            "slot": "weapon",
            "canBeThrownAway": true,
            "slotsNumber": 1,
            "requirements": {
                "physique": 5,
                "agility": 5
            },
            "range": {
                "maximumX": 1,
                "maximumY": 2
            },
            "damage": [
                {
                    "chance": 65,
                    "cutting": 14,
                    "deviation": 2
                },
                {
                    "duration": 3,
                    "chance": 10,
                    "bleeding": 5,
                    "deviation": 3
                }
            ],
            "useCost": {
                "stamina": 5,
                "actionPoints": 4
            }
        },
        {
            "type": "weapon",
            "name": "Dagger",
            "code": "dagger-02",
            "description": "A rogue's companion, its edge eager to taste the blood of the unwary.",
            "durability": 300,
            "slot": "weapon",
            "canBeSold": true,
            "canBeThrownAway": true,
            "slotsNumber": 1,
            "requirements": {
                "physique": 5,
                "agility": 7
            },
            "range": {
                "maximumX": 1,
                "maximumY": 2
            },
            "damage": [
                {
                    "chance": 75,
                    "cutting": 24,
                    "deviation": 2
                },
                {
                    "duration": 3,
                    "chance": 15,
                    "bleeding": 8,
                    "deviation": 3
                }
            ],
            "useCost": {
                "stamina": 7,
                "actionPoints": 4
            },
            "price": {
                "coins": 1000
            }
        },
        {
            "type": "weapon",
            "name": "Staff",
            "code": "sorcerer-staff-01",
            "description": "A gnarled staff, humming with arcane power. The mark of a true sorcerer.",
            "ammunitionKind": "magicCharge",
            "slot": "weapon",
            "canBeThrownAway": true,
            "slotsNumber": 2,
            "requirements": {
                "intelligence": 8
            },
            "damage": [
                {
                    "chance": 65
                }
            ],
            "range": {
                "maximumX": 5,
                "minimumX": 2,
                "maximumY": 5
            },
            "useCost": {
                "mana": 5,
                "stamina": 2,
                "actionPoints": 5
            }
        },
        {
            "type": "weapon",
            "name": "Scare Staff",
            "code": "sorcerer-staff-02",
            "description": "A staff crowned with a skull, radiating dread and the promise of nightmares.",
            "ammunitionKind": "magicCharge",
            "durability": 300,
            "slot": "weapon",
            "canBeSold": true,
            "canBeThrownAway": true,
            "slotsNumber": 2,
            "requirements": {
                "intelligence": 12
            },
            "damage": [
                {
                    "chance": 75,
                    "fear": 5
                }
            ],
            "range": {
                "maximumX": 5,
                "minimumX": 2,
                "maximumY": 5
            },
            "useCost": {
                "mana": 7,
                "stamina": 3,
                "actionPoints": 5
            },
            "price": {
                "coins": 3000,
                "ruby": 10
            }
        },
        {
            "type": "weapon",
            "name": "Axe",
            "code": "axe-01",
            "description": "A brutal axe, its blade chipped and stained with the memories of old massacres.",
            "slot": "weapon",
            "canBeThrownAway": true,
            "slotsNumber": 2,
            "requirements": {
                "strength": 10
            },
            "range": {
                "maximumX": 1,
                "maximumY": 2
            },
            "useCost": {
                "stamina": 12,
                "actionPoints": 4
            },
            "damage": [
                {
                    "chance": 60,
                    "cutting": 22,
                    "crushing": 2,
                    "deviation": 5
                },
                {
                    "duration": 3,
                    "chance": 5,
                    "bleeding": 5,
                    "deviation": 1
                }
            ]
        },
        {
            "type": "weapon",
            "name": "Axe",
            "code": "axe-02",
            "description": "A heavy axe, forged for war and the splitting of skulls.",
            "durability": 300,
            "slot": "weapon",
            "canBeSold": true,
            "canBeThrownAway": true,
            "slotsNumber": 2,
            "requirements": {
                "strength": 15
            },
            "range": {
                "maximumX": 1,
                "maximumY": 2
            },
            "useCost": {
                "stamina": 14,
                "actionPoints": 5
            },
            "damage": [
                {
                    "chance": 70,
                    "cutting": 32,
                    "crushing": 7,
                    "deviation": 5
                },
                {
                    "duration": 3,
                    "chance": 15,
                    "bleeding": 5
                }
            ],
            "price": {
                "coins": 2000
            }
        },
        {
            "type": "weapon",
            "name": "Scythe",
            "code": "scythe-01",
            "description": "A reaper's scythe, its curved blade thirsting for souls beneath the pale moon.",
            "durability": 300,
            "slot": "weapon",
            "canBeSold": true,
            "canBeThrownAway": true,
            "slotsNumber": 2,
            "requirements": {
                "strength": 10
            },
            "range": {
                "maximumX": 1,
                "maximumY": 2
            },
            "useCost": {
                "stamina": 25,
                "actionPoints": 6
            },
            "damage": [
                {
                    "chance": 60,
                    "cutting": 34,
                    "stubbing": 4,
                    "fear": 4,
                    "deviation": 2
                },
                {
                    "duration": 3,
                    "chance": 30,
                    "bleeding": 10,
                    "deviation": 1
                }
            ],
            "price": {
                "coins": 3000
            }
        },
        {
            "type": "weapon",
            "name": "Rusty Mace",
            "code": "rusty-mace-01",
            "description": "A corroded mace, heavy and cruel. Its blows shatter bone and hope alike.",
            "durability": 50,
            "slot": "weapon",
            "canBeSold": true,
            "canBeThrownAway": true,
            "slotsNumber": 1,
            "requirements": {
                "strength": 5
            },
            "range": {
                "maximumX": 1,
                "maximumY": 2
            },
            "useCost": {
                "stamina": 15,
                "actionPoints": 5
            },
            "damage": [
                {
                    "chance": 55,
                    "cutting": 2,
                    "crushing": 27,
                    "deviation": 5
                },
                {
                    "duration": 3,
                    "chance": 15,
                    "bleeding": 2,
                    "deviation": 1
                }
            ],
            "price": {
                "coins": 250
            }
        },
        {
            "type": "weapon",
            "name": "Rusty Axe",
            "code": "rusty-axe-01",
            "description": "A battered axe, its edge jagged and eager to bite into flesh.",
            "durability": 50,
            "slot": "weapon",
            "canBeSold": true,
            "canBeThrownAway": true,
            "slotsNumber": 1,
            "requirements": {
                "strength": 5
            },
            "range": {
                "maximumX": 1,
                "maximumY": 2
            },
            "useCost": {
                "stamina": 13,
                "actionPoints": 5
            },
            "damage": [
                {
                    "chance": 55,
                    "cutting": 24,
                    "crushing": 4,
                    "deviation": 2
                },
                {
                    "duration": 3,
                    "chance": 15,
                    "bleeding": 2,
                    "deviation": 1
                }
            ],
            "price": {
                "coins": 200
            }
        }
    ],
    "magic": [
        {
            "type": "magic",
            "name": "Sm Treatment",
            "description": "A whispered incantation, weaving faint threads of life into wounded flesh. The touch of hope in a world of agony.",
            "code": "magic-health-01",
            "price": {
                "coins": 1200,
                "ruby": 2
            },
            "requirements": {
                "intelligence": 8
            },
            "range": {
                "maximumX": 10,
                "maximumY": 10
            },
            "useCost": {
                "mana": 15,
                "actionPoints": 5
            },
            "damage": [],
            "modification": [
                {
                    "recovery": {
                        "health": 25,
                        "deviation": 5
                    }
                }
            ]
        },
        {
            "type": "magic",
            "name": "Rg Treatment",
            "description": "A ritual of blood and will, mending grievous wounds and staving off the cold embrace of death.",
            "code": "magic-health-02",
            "price": {
                "coins": 2000,
                "ruby": 5
            },
            "requirements": {
                "intelligence": 12
            },
            "range": {
                "maximumX": 10,
                "maximumY": 10
            },
            "useCost": {
                "mana": 30,
                "actionPoints": 6
            },
            "damage": [],
            "modification": [
                {
                    "recovery": {
                        "health": 50,
                        "deviation": 5
                    }
                }
            ]
        },
        {
            "type": "magic",
            "name": "Sm Stamina",
            "description": "A fleeting surge of vigor, summoned from forgotten spirits. Muscles burn with unnatural strength.",
            "code": "magic-stamina-01",
            "price": {
                "coins": 800
            },
            "requirements": {
                "intelligence": 8
            },
            "range": {
                "maximumX": 10,
                "maximumY": 10
            },
            "useCost": {
                "mana": 10,
                "actionPoints": 4
            },
            "damage": [],
            "modification": [
                {
                    "recovery": {
                        "stamina": 25,
                        "deviation": 5
                    }
                }
            ]
        },
        {
            "type": "magic",
            "name": "Rg Stamina",
            "description": "A chant that fills weary limbs with the relentless energy of the abyss. Endurance for the damned.",
            "code": "magic-stamina-02",
            "price": {
                "coins": 1500,
                "ruby": 3
            },
            "requirements": {
                "intelligence": 10
            },
            "range": {
                "maximumX": 10,
                "maximumY": 10
            },
            "useCost": {
                "mana": 20,
                "actionPoints": 5
            },
            "damage": [],
            "modification": [
                {
                    "recovery": {
                        "stamina": 50,
                        "deviation": 5
                    }
                }
            ]
        }
    ],
    "armor": [
        {
            "type": "armor",
            "name": "Rusty Helmet",
            "code": "rusty-helmet-01",
            "description": "A battered helm, its iron pitted and stained by the blood of forgotten battles. Offers scant protection, but better than a bare skull beneath the moon.",
            "price": {
                "coins": 30
            },
            "durability": 50,
            "slot": "head",
            "canBeSold": true,
            "canBeThrownAway": true,
            "slotsNumber": 1,
            "requirements": {
                "strength": 2
            },
            "modification": [
                {
                    "resistance": {
                        "stabbing": 1,
                        "crushing": 1
                    }
                }
            ]
        },
        {
            "type": "armor",
            "name": "Rusty Boots",
            "code": "rusty-boots-01",
            "description": "Boots of cracked leather and rusted buckles, worn by countless miles and misery. Each step echoes with the ghosts of the fallen.",
            "price": {
                "coins": 30
            },
            "durability": 50,
            "slot": "leg",
            "canBeSold": true,
            "canBeThrownAway": true,
            "slotsNumber": 2,
            "requirements": {
                "strength": 2,
                "physique": 2
            },
            "modification": [
                {
                    "resistance": {
                        "stabbing": 1,
                        "cutting": 1
                    }
                }
            ]
        },
        {
            "type": "armor",
            "name": "Rusty Shield",
            "code": "rusty-shield-01",
            "description": "A splintered shield, its surface marred by axe and arrow. It has turned aside death more than once, but its time is nearly spent.",
            "price": {
                "coins": 50
            },
            "durability": 50,
            "slot": "weapon",
            "canBeSold": true,
            "canBeThrownAway": true,
            "slotsNumber": 1,
            "requirements": {
                "strength": 3,
                "physique": 3
            },
            "modification": [
                {
                    "resistance": {
                        "stabbing": 1,
                        "cutting": 1,
                        "crushing": 1
                    }
                }
            ]
        },
        {
            "type": "armor",
            "name": "Rag",
            "code": "rag-armor-01",
            "description": "Tattered rags, barely worthy of the name 'armor.' They offer little more than the illusion of safety.",
            "price": {
                "coins": 50
            },
            "durability": 50,
            "slot": "body",
            "canBeSold": true,
            "canBeThrownAway": true,
            "slotsNumber": 1,
            "requirements": {
                "strength": 1,
                "physique": 1
            },
            "modification": [
                {
                    "resistance": {
                        "stabbing": 1,
                        "cutting": 1,
                        "crushing": 1
                    }
                }
            ]
        },
        {
            "type": "armor",
            "name": "Helmet",
            "code": "helmet-01",
            "description": "A sturdy helmet, forged for those who expect to meet death and wish to spit in its face.",
            "durability": 500,
            "slot": "head",
            "canBeSold": true,
            "canBeThrownAway": true,
            "slotsNumber": 1,
            "requirements": {
                "strength": 3,
                "physique": 3
            },
            "modification": [
                {
                    "resistance": {
                        "stabbing": 2,
                        "cutting": 2,
                        "crushing": 2,
                        "bleeding": 2
                    }
                }
            ],
            "price": {
                "coins": 450
            }
        },
        {
            "type": "armor",
            "name": "Boots",
            "code": "boots-01",
            "description": "Boots of thick hide, their soles worn thin by endless marches through mud and blood.",
            "durability": 500,
            "slot": "leg",
            "canBeSold": true,
            "canBeThrownAway": true,
            "slotsNumber": 2,
            "requirements": {
                "strength": 3,
                "physique": 3
            },
            "modification": [
                {
                    "resistance": {
                        "stabbing": 2,
                        "cutting": 2,
                        "crushing": 2
                    }
                }
            ],
            "price": {
                "coins": 400
            }
        },
        {
            "type": "armor",
            "name": "Fine Boots",
            "code": "boots-02",
            "description": "Boots of supple leather, crafted for nobles but stained by the road. They whisper of both privilege and peril.",
            "durability": 500,
            "slot": "leg",
            "canBeSold": true,
            "canBeThrownAway": true,
            "slotsNumber": 2,
            "requirements": {
                "strength": 3,
                "physique": 3
            },
            "modification": [
                {
                    "resistance": {
                        "stabbing": 3,
                        "cutting": 3,
                        "crushing": 3
                    }
                }
            ],
            "price": {
                "coins": 1000
            }
        },
        {
            "type": "armor",
            "name": "Gloves",
            "code": "gloves-01",
            "description": "Gloves of rough leather, their seams darkened by sweat and old blood. They shield the hands from more than just the cold.",
            "durability": 500,
            "slot": "hand",
            "canBeSold": true,
            "canBeThrownAway": true,
            "slotsNumber": 2,
            "requirements": {
                "strength": 3,
                "physique": 3
            },
            "modification": [
                {
                    "resistance": {
                        "stabbing": 1,
                        "cutting": 1,
                        "crushing": 1
                    }
                }
            ],
            "price": {
                "coins": 300
            }
        },
        {
            "type": "armor",
            "name": "Fine Gloves",
            "code": "gloves-02",
            "description": "Gloves of masterwork make, their touch as deft as a thief's and as sure as a duelist's.",
            "durability": 500,
            "slot": "hand",
            "canBeSold": true,
            "canBeThrownAway": true,
            "slotsNumber": 2,
            "requirements": {
                "strength": 3,
                "physique": 3
            },
            "modification": [
                {
                    "resistance": {
                        "stabbing": 2,
                        "cutting": 2,
                        "crushing": 2
                    }
                }
            ],
            "price": {
                "coins": 700
            }
        },
        {
            "type": "armor",
            "name": "Light Gloves",
            "code": "lightning-gloves-01",
            "description": "Gloves woven with silver thread, crackling faintly with arcane lightning. Each strike is charged with the storm's fury.",
            "durability": 500,
            "slot": "hand",
            "canBeSold": true,
            "canBeThrownAway": true,
            "slotsNumber": 2,
            "requirements": {
                "strength": 3,
                "physique": 3
            },
            "modification": [
                {
                    "resistance": {
                        "stabbing": 2,
                        "cutting": 2,
                        "crushing": 2
                    },
                    "damage": {
                        "lightning": 8
                    }
                }
            ],
            "price": {
                "coins": 1000
            }
        },
        {
            "type": "armor",
            "name": "Shield",
            "code": "shield-01",
            "description": "A broad shield, its face scarred by a hundred blows. It stands as a bulwark between its bearer and the abyss.",
            "durability": 500,
            "slot": "weapon",
            "canBeSold": true,
            "canBeThrownAway": true,
            "slotsNumber": 1,
            "requirements": {
                "strength": 5,
                "physique": 5
            },
            "modification": [
                {
                    "resistance": {
                        "stabbing": 3,
                        "cutting": 3,
                        "crushing": 3
                    }
                }
            ],
            "price": {
                "coins": 700
            }
        },
        {
            "type": "armor",
            "name": "Armor",
            "code": "armor-01",
            "description": "A cuirass of boiled leather, bearing the scars of many battles. It creaks with every breath, a reminder of survival.",
            "durability": 500,
            "slot": "body",
            "canBeSold": true,
            "canBeThrownAway": true,
            "slotsNumber": 1,
            "requirements": {
                "strength": 5,
                "physique": 5
            },
            "modification": [
                {
                    "resistance": {
                        "stabbing": 4,
                        "cutting": 4,
                        "crushing": 4,
                        "bleeding": 2
                    }
                }
            ],
            "price": {
                "coins": 1500
            }
        },
        {
            "type": "armor",
            "name": "Hat",
            "description": "A pointed hat of midnight blue, worn by those who consort with shadows and secrets. Its brim hides both wisdom and madness.",
            "code": "sorcerer-hat-01",
            "price": {
                "coins": 450,
                "ruby": 2
            },
            "durability": 500,
            "slot": "head",
            "canBeSold": true,
            "canBeThrownAway": true,
            "slotsNumber": 1,
            "requirements": {
                "intelligence": 8
            },
            "modification": [
                {
                    "baseAttributes": {
                        "mana": 10
                    },
                    "resistance": {
                        "fire": 2,
                        "cold": 2,
                        "lightning": 2,
                        "poison": 2,
                        "exhaustion": 2,
                        "manaDrain": 2
                    }
                }
            ]
        },
        {
            "type": "armor",
            "name": "Mana Neck",
            "description": "A necklace strung with shards of sapphire, pulsing with arcane energy. It shields the soul from the hungers of the void.",
            "code": "necklace-01",
            "price": {
                "coins": 450
            },
            "durability": 500,
            "slot": "neck",
            "canBeSold": true,
            "canBeThrownAway": true,
            "slotsNumber": 1,
            "requirements": {
                "intelligence": 8
            },
            "modification": [
                {
                    "recovery": {
                        "mana": 4
                    },
                    "resistance": {
                        "manaDrain": 2
                    }
                }
            ]
        },
        {
            "type": "armor",
            "name": "Initi Neck",
            "description": "A chain of black iron, worn by those who would seize fate before it seizes them. It sharpens the mind for the coming storm.",
            "code": "necklace-02",
            "price": {
                "coins": 450
            },
            "durability": 500,
            "slot": "neck",
            "canBeSold": true,
            "canBeThrownAway": true,
            "slotsNumber": 1,
            "requirements": {},
            "modification": [
                {
                    "attributes": {
                        "initiative": 4
                    }
                }
            ]
        },
        {
            "type": "armor",
            "name": "Agili Neck",
            "description": "A slender chain, light as a whisper, granting its wearer the swiftness of a shadow fleeing the dawn.",
            "code": "necklace-03",
            "price": {
                "coins": 450
            },
            "durability": 500,
            "slot": "neck",
            "canBeSold": true,
            "canBeThrownAway": true,
            "slotsNumber": 1,
            "requirements": {},
            "modification": [
                {
                    "attributes": {
                        "agility": 4
                    }
                }
            ]
        },
        {
            "type": "armor",
            "name": "Cloak",
            "description": "A cloak woven from midnight and mystery, favored by those who walk the hidden paths of power.",
            "code": "sorcerer-cloak-01",
            "price": {
                "coins": 1200,
                "ruby": 5
            },
            "durability": 500,
            "slot": "body",
            "canBeSold": true,
            "canBeThrownAway": true,
            "slotsNumber": 1,
            "requirements": {
                "intelligence": 8
            },
            "modification": [
                {
                    "baseAttributes": {
                        "mana": 20
                    },
                    "resistance": {
                        "fire": 4,
                        "cold": 4,
                        "lightning": 4,
                        "poison": 2,
                        "exhaustion": 4,
                        "manaDrain": 3,
                        "bleeding": 2
                    },
                    "recovery": {
                        "health": 5,
                        "mana": 10,
                        "bleeding": 3
                    }
                }
            ]
        }
    ],
    "disposable": [
        {
            "name": "Health Sm",
            "type": "disposable",
            "code": "health-potion-01",
            "description": "A vial of crimson elixir, rumored to be distilled from the blood of saints and sinners alike. Its warmth staves off death, if only for a while.",
            "canBeSold": true,
            "canBeThrownAway": true,
            "modification": [
                {
                    "recovery": {
                        "health": 50,
                        "deviation": 5
                    }
                },
                {
                    "chance": 50,
                    "duration": 5,
                    "recovery": {
                        "health": 2,
                        "deviation": 1
                    }
                }
            ],
            "price": {
                "coins": 25
            },
            "useCost": {
                "actionPoints": 4
            }
        },
        {
            "name": "Stamina Sm",
            "type": "disposable",
            "code": "stamina-potion-01",
            "description": "A flask of bitter draught, brewed by witches in the wild. It fills the weary with a fleeting surge of vigor.",
            "canBeSold": true,
            "canBeThrownAway": true,
            "modification": [
                {
                    "recovery": {
                        "stamina": 50,
                        "deviation": 5
                    }
                },
                {
                    "chance": 50,
                    "duration": 5,
                    "recovery": {
                        "stamina": 2,
                        "deviation": 1
                    }
                }
            ],
            "price": {
                "coins": 25
            },
            "useCost": {
                "actionPoints": 4
            }
        },
        {
            "name": "Mana Sm",
            "type": "disposable",
            "code": "mana-potion-01",
            "description": "A bottle of shimmering blue liquid, cold as the grave and sharp as a wizard's wit. Restores the mind's arcane fire.",
            "canBeSold": true,
            "canBeThrownAway": true,
            "modification": [
                {
                    "recovery": {
                        "mana": 50,
                        "deviation": 5
                    }
                },
                {
                    "chance": 50,
                    "duration": 5,
                    "recovery": {
                        "mana": 2,
                        "deviation": 1
                    }
                }
            ],
            "price": {
                "coins": 30
            },
            "useCost": {
                "actionPoints": 4
            }
        },
        {
            "name": "Agility Sm",
            "type": "disposable",
            "code": "agility-potion-01",
            "description": "A draught of quicksilver and shadow, said to grant the swiftness of a midnight fox to those who dare drink.",
            "canBeSold": true,
            "canBeThrownAway": true,
            "modification": [
                {
                    "duration": 5,
                    "attributes": {
                        "agility": 4,
                        "deviation": 1
                    }
                }
            ],
            "price": {
                "coins": 35
            },
            "useCost": {
                "actionPoints": 4
            }
        },
        {
            "name": "Poison",
            "type": "disposable",
            "code": "poison-01",
            "description": "A vial of virulent green venom, harvested from the fangs of night serpents. One drop can spell a slow, agonizing death.",
            "canBeSold": true,
            "canBeThrownAway": true,
            "damage": [
                {
                    "duration": 3,
                    "poison": 15,
                    "deviation": 1
                }
            ],
            "price": {
                "coins": 25
            },
            "useCost": {
                "actionPoints": 5
            }
        },
        {
            "name": "Bandage",
            "type": "disposable",
            "code": "bandage-01",
            "description": "A strip of linen, stained by old wounds and desperate prayers. Slows the bleeding, if not the pain.",
            "canBeSold": true,
            "canBeThrownAway": true,
            "modification": [
                {
                    "recovery": {
                        "bleeding": 50,
                        "deviation": 5
                    }
                }
            ],
            "price": {
                "coins": 25
            },
            "useCost": {
                "actionPoints": 4
            }
        },
        {
            "type": "disposable",
            "name": "Bomb",
            "code": "bomb-01",
            "description": "A crude iron sphere packed with black powder and spite. Hurl it into the fray and watch the world burn.",
            "canBeSold": true,
            "canBeThrownAway": true,
            "price": {
                "coins": 60
            },
            "range": {
                "maximumX": 10,
                "maximumY": 10
            },
            "damage": [
                {
                    "fire": 60,
                    "deviation": 5
                },
                {
                    "duration": 3,
                    "chance": 10,
                    "fire": 8,
                    "deviation": 4
                }
            ],
            "spread": [
                {
                    "y": 1
                },
                {
                    "y": -1
                }
            ],
            "modification": [],
            "useCost": {
                "actionPoints": 6
            }
        }
    ],
    "ammunition": [
        {
            "name": "Arrow",
            "type": "ammunition",
            "code": "arrow-01",
            "description": "A simple arrow, its iron tip dulled by rain and time. Still, it finds flesh when loosed by a steady hand.",
            "kind": "arrow",
            "canBeSold": true,
            "canBeThrownAway": true,
            "damage": [
                {
                    "stabbing": 24,
                    "deviation": 2
                },
                {
                    "duration": 3,
                    "chance": 15,
                    "bleeding": 3,
                    "deviation": 1
                }
            ],
            "price": {
                "coins": 2
            }
        },
        {
            "name": "Fire Arrow",
            "type": "ammunition",
            "code": "arrow-fire-01",
            "description": "An arrow wrapped in pitch and set alight, trailing embers as it seeks its mark. Its fire is as merciless as its steel.",
            "kind": "arrow",
            "canBeSold": true,
            "canBeThrownAway": true,
            "damage": [
                {
                    "stabbing": 20,
                    "fire": 14,
                    "deviation": 2
                },
                {
                    "duration": 3,
                    "chance": 15,
                    "bleeding": 3,
                    "fire": 3,
                    "deviation": 1
                }
            ],
            "price": {
                "coins": 5
            }
        },
        {
            "name": "Frost Arrow",
            "type": "ammunition",
            "code": "arrow-frost-01",
            "description": "An arrow rimed with hoarfrost, its chill biting deeper than steel. It leaves wounds that never truly warm.",
            "kind": "arrow",
            "canBeSold": true,
            "canBeThrownAway": true,
            "damage": [
                {
                    "stabbing": 20,
                    "cold": 14,
                    "deviation": 2
                },
                {
                    "duration": 3,
                    "chance": 15,
                    "bleeding": 3,
                    "cold": 3,
                    "deviation": 1
                }
            ],
            "price": {
                "coins": 5
            }
        },
        {
            "name": "Light Arrow",
            "type": "ammunition",
            "code": "arrow-lightning-01",
            "description": "An arrow tipped with a shard of storm, crackling with barely contained lightning. Its strike is swift and blinding.",
            "kind": "arrow",
            "canBeSold": true,
            "canBeThrownAway": true,
            "damage": [
                {
                    "stabbing": 20,
                    "lightning": 14,
                    "deviation": 2
                },
                {
                    "duration": 3,
                    "chance": 15,
                    "bleeding": 3,
                    "lightning": 3,
                    "deviation": 1
                }
            ],
            "price": {
                "coins": 5
            }
        },
        {
            "name": "Poison Chrg",
            "type": "ammunition",
            "code": "poison-charge-01",
            "description": "A glass vial brimming with venomous mist, meant for a sorcerer's staff. Its touch brings a slow, inevitable demise.",
            "kind": "magicCharge",
            "canBeSold": true,
            "canBeThrownAway": true,
            "damage": [
                {
                    "poison": 24,
                    "deviation": 2
                },
                {
                    "duration": 3,
                    "chance": 15,
                    "poison": 5,
                    "deviation": 1
                }
            ],
            "price": {
                "coins": 5
            }
        },
        {
            "name": "Fire Charge",
            "type": "ammunition",
            "code": "fire-charge-01",
            "description": "A flask of burning essence, used to fuel a sorcerer's wrath. It bursts into flame with a whisper of the old tongue.",
            "kind": "magicCharge",
            "canBeSold": true,
            "canBeThrownAway": true,
            "damage": [
                {
                    "fire": 24,
                    "deviation": 2
                },
                {
                    "duration": 3,
                    "chance": 15,
                    "fire": 5,
                    "deviation": 1
                }
            ],
            "price": {
                "coins": 3
            }
        },
        {
            "name": "Fire Charge",
            "type": "ammunition",
            "code": "fire-charge-02",
            "description": "A dragon's breath, captured in a fragile vessel. When unleashed, it scorches all in its path.",
            "kind": "magicCharge",
            "canBeSold": true,
            "canBeThrownAway": true,
            "damage": [
                {
                    "fire": 48,
                    "deviation": 5
                },
                {
                    "duration": 3,
                    "chance": 15,
                    "fire": 12,
                    "deviation": 5
                }
            ],
            "price": {
                "coins": 3
            }
        },
        {
            "name": "Cold Charge",
            "type": "ammunition",
            "code": "cold-charge-01",
            "description": "A crystal of eternal frost, humming with the promise of winter's bite. It chills the soul as well as the flesh.",
            "kind": "magicCharge",
            "canBeSold": true,
            "canBeThrownAway": true,
            "damage": [
                {
                    "cold": 24,
                    "deviation": 2
                },
                {
                    "duration": 3,
                    "chance": 15,
                    "cold": 5,
                    "deviation": 1
                }
            ],
            "price": {
                "coins": 3
            }
        },
        {
            "name": "Light Chrg",
            "type": "ammunition",
            "code": "lightning-charge-01",
            "description": "A vial of bottled lightning, restless and wild. It crackles with the fury of a midnight storm.",
            "kind": "magicCharge",
            "canBeSold": true,
            "canBeThrownAway": true,
            "damage": [
                {
                    "lightning": 24,
                    "deviation": 2
                },
                {
                    "duration": 3,
                    "chance": 15,
                    "lightning": 5,
                    "deviation": 1
                }
            ],
            "price": {
                "coins": 3
            }
        }
    ],
    "provision": [
        {
            "type": "provision",
            "name": "Ham",
            "description": "A slab of smoked ham, its savory scent a fleeting comfort in a world of hunger and hardship. Restores strength to the weary.",
            "code": "provision-ham-01",
            "canBeThrownAway": true,
            "canBeSold": true,
            "price": {
                "coins": 20
            },
            "recovery": {
                "health": 70
            }
        },
        {
            "type": "provision",
            "name": "Pumpkin",
            "description": "A plump pumpkin, its flesh sweet and hearty. A humble feast for those who survive on the edge of darkness.",
            "code": "provision-pumpkin-01",
            "canBeThrownAway": true,
            "canBeSold": true,
            "price": {
                "coins": 20
            },
            "recovery": {
                "stamina": 70
            }
        },
        {
            "type": "provision",
            "name": "Wine",
            "description": "A bottle of deep red wine, swirling with the memories of forgotten revels. Its warmth stirs the soul and sharpens the mind.",
            "code": "provision-wine-01",
            "canBeThrownAway": true,
            "canBeSold": true,
            "price": {
                "coins": 25
            },
            "recovery": {
                "mana": 70
            }
        },
        {
            "type": "provision",
            "name": "Salad",
            "description": "A bowl of wild greens and roots, gathered from the haunted woods.",
            "code": "provision-salad-01",
            "canBeThrownAway": true,
            "canBeSold": true,
            "price": {
                "coins": 30
            },
            "recovery": {
                "stamina": 100,
                "mana": 10
            }
        },
        {
            "type": "provision",
            "name": "Fried Rice",
            "description": "A rare treat of fried rice, speckled with morsels of meat and herbs. A banquet for the fortunate, a memory for the lost.",
            "code": "provision-fried-rice-01",
            "canBeThrownAway": true,
            "canBeSold": true,
            "price": {
                "coins": 50
            },
            "recovery": {
                "health": 80,
                "stamina": 80,
                "mana": 30
            }
        }
    ]
}