[
    {
        "name": "Barbarian",
        "code": "barbarian",
        "booty": {
            "coins": 300
        },
        "stats": {
            "progress": {
                "level": 1
            },
            "baseAttributes": {
                "health": 80,
                "stamina": 80
            },
            "attributes": {
                "strength": 10,
                "physique": 8,
                "agility": 2,
                "endurance": 10,
                "intelligence": 0,
                "initiative": 0,
                "luck": 5
            },
            "resistance": {
                "stabbing": 5,
                "cutting": 5,
                "crushing": 5,
                "fire": 0,
                "cold": 8,
                "lighting": 0,
                "poison": 0,
                "exhaustion": 5,
                "manaDrain": 0,
                "bleeding": 2,
                "fear": 5,
                "curse": 0,
                "madness": 0
            }
        },
        "inventory": {
            "descriptor": [
                {
                    "code": "fist-01"
                },
                {
                    "code": "axe-01",
                    "equipped": true
                }
            ]
        },
        "slots": {
            "head": 1,
            "neck": 1,
            "body": 1,
            "hand": 2,
            "leg": 2,
            "weapon": 2
        }
    },
    {
        "name": "Tank",
        "code": "tank",
        "booty": {
            "coins": 300
        },
        "stats": {
            "progress": {
                "level": 1
            },
            "baseAttributes": {
                "health": 75,
                "stamina": 75
            },
            "attributes": {
                "strength": 8,
                "physique": 8,
                "agility": 3,
                "endurance": 7,
                "intelligence": 2,
                "initiative": 2,
                "luck": 5
            },
            "resistance": {
                "stabbing": 5,
                "cutting": 5,
                "crushing": 5,
                "fire": 0,
                "cold": 0,
                "lighting": 0,
                "poison": 0,
                "exhaustion": 3,
                "manaDrain": 0,
                "bleeding": 3,
                "fear": 5,
                "curse": 2,
                "madness": 2
            }
        },
        "inventory": {
            "descriptor": [
                {
                    "code": "fist-01"
                },
                {
                    "code": "sword-01",
                    "equipped": true
                }
            ]
        },
        "slots": {
            "head": 1,
            "neck": 1,
            "body": 1,
            "hand": 2,
            "leg": 2,
            "weapon": 2
        }
    },
    {
        "name": "Spearsman",
        "code": "spearsman",
        "booty": {
            "coins": 300
        },
        "stats": {
            "progress": {
                "level": 1
            },
            "baseAttributes": {
                "health": 60,
                "stamina": 60
            },
            "attributes": {
                "strength": 7,
                "physique": 7,
                "agility": 7,
                "endurance": 5,
                "intelligence": 2,
                "initiative": 2,
                "luck": 5
            },
            "resistance": {
                "stabbing": 5,
                "cutting": 5,
                "crushing": 5,
                "fire": 0,
                "cold": 0,
                "lighting": 0,
                "poison": 0,
                "exhaustion": 3,
                "manaDrain": 0,
                "bleeding": 5,
                "fear": 3,
                "curse": 0,
                "madness": 0
            }
        },
        "inventory": {
            "descriptor": [
                {
                    "code": "fist-01"
                },
                {
                    "code": "spear-01",
                    "equipped": true
                }
            ]
        },
        "slots": {
            "head": 1,
            "neck": 1,
            "body": 1,
            "hand": 2,
            "leg": 2,
            "weapon": 2
        }
    },
    {
        "name": "Rogue",
        "code": "rogue",
        "booty": {
            "coins": 300
        },
        "stats": {
            "progress": {
                "level": 1
            },
            "baseAttributes": {
                "health": 50,
                "stamina": 50
            },
            "attributes": {
                "strength": 5,
                "physique": 5,
                "agility": 8,
                "endurance": 5,
                "intelligence": 2,
                "initiative": 7,
                "luck": 5
            },
            "resistance": {
                "stabbing": 5,
                "cutting": 5,
                "crushing": 5,
                "fire": 0,
                "cold": 0,
                "lighting": 0,
                "poison": 5,
                "exhaustion": 0,
                "manaDrain": 0,
                "bleeding": 5,
                "fear": 0,
                "curse": 0,
                "madness": 0
            }
        },
        "inventory": {
            "descriptor": [
                {
                    "code": "fist-01"
                },
                {
                    "code": "bow-01",
                    "equipped": true
                },
                {
                    "code": "dagger-01"
                },
                {
                    "code": "arrow-01",
                    "equipped": true,
                    "quantity": 30
                }
            ]
        },
        "slots": {
            "head": 1,
            "neck": 1,
            "body": 1,
            "hand": 2,
            "leg": 2,
            "weapon": 2
        }
    },
    {
        "name": "Mage",
        "code": "mage",
        "booty": {
            "coins": 300
        },
        "stats": {
            "progress": {
                "level": 1
            },
            "baseAttributes": {
                "health": 50,
                "stamina": 50,
                "mana": 75
            },
            "attributes": {
                "strength": 2,
                "physique": 2,
                "agility": 2,
                "endurance": 3,
                "intelligence": 10,
                "initiative": 8,
                "luck": 8
            },
            "resistance": {
                "stabbing": 0,
                "cutting": 0,
                "crushing": 0,
                "fire": 5,
                "cold": 5,
                "lighting": 5,
                "poison": 0,
                "exhaustion": 0,
                "manaDrain": 5,
                "bleeding": 0,
                "fear": 0,
                "curse": 5,
                "madness": 5
            }
        },
        "inventory": {
            "descriptor": [
                {
                    "code": "fist-01"
                },
                {
                    "code": "sorcerer-staff-01",
                    "equipped": true
                },
                {
                    "code": "fire-charge-01",
                    "quantity": 10,
                    "equipped": true
                },
                {
                    "code": "cold-charge-01",
                    "quantity": 10
                },
                {
                    "code": "lighting-charge-01",
                    "quantity": 10
                },
                {
                    "code": "magic-health-01"
                },
                {
                    "code": "magic-stamina-01"
                }
            ]
        },
        "slots": {
            "head": 1,
            "neck": 1,
            "body": 1,
            "hand": 2,
            "leg": 2,
            "weapon": 2
        }
    },
    {
        "name": "North Troll",
        "code": "troll-01",
        "stats": {
            "progress": {
                "level": 10,
                "experience": 150
            },
            "baseAttributes": {
                "health": 200,
                "stamina": 200
            },
            "attributes": {
                "strength": 15,
                "physique": 20,
                "agility": 5,
                "endurance": 30,
                "intelligence": 0,
                "initiative": 0,
                "luck": 5
            },
            "resistance": {
                "stabbing": 0,
                "cutting": 0,
                "crushing": 20,
                "fire": 0,
                "cold": 50,
                "lighting": 0,
                "poison": 0,
                "exhaustion": 10,
                "manaDrain": 0,
                "bleeding": 0,
                "fear": 0,
                "curse": 0,
                "madness": 0
            }
        },
        "slots": {
            "head": 1,
            "neck": 1,
            "body": 1,
            "hand": 2,
            "leg": 2,
            "weapon": 2
        },
        "inventory": {
            "descriptor": [
                {
                    "code": "fist-01"
                },
                {
                    "code": "rusty-axe-01",
                    "equipped": true
                },
                {
                    "code": "rusty-helmet-01",
                    "equipped": true
                }
            ]
        }
    },
    {
        "name": "Nasty Goblin",
        "code": "goblin-01",
        "stats": {
            "progress": {
                "level": 10,
                "experience": 70
            },
            "baseAttributes": {
                "health": 100,
                "stamina": 100
            },
            "attributes": {
                "strength": 10,
                "physique": 5,
                "agility": 12,
                "endurance": 15,
                "intelligence": 0,
                "initiative": 5,
                "luck": 5
            },
            "resistance": {
                "stabbing": 5,
                "cutting": 5,
                "crushing": 0,
                "fire": 0,
                "cold": 0,
                "lighting": 0,
                "poison": 15,
                "exhaustion": 0,
                "manaDrain": 0,
                "bleeding": 0,
                "fear": 0,
                "curse": 0,
                "madness": 0
            }
        },
        "slots": {
            "head": 1,
            "neck": 1,
            "body": 1,
            "hand": 2,
            "leg": 2,
            "weapon": 2
        },
        "inventory": {
            "descriptor": [
                {
                    "code": "fist-01"
                },
                {
                    "code": "rusty-mace-01",
                    "equipped": true
                },
                {
                    "code": "rusty-helmet-01",
                    "equipped": true
                }
            ]
        }
    },
    {
        "name": "Bat",
        "code": "bat-01",
        "stats": {
            "progress": {
                "level": 2,
                "experience": 25
            },
            "baseAttributes": {
                "health": 50,
                "stamina": 50
            },
            "attributes": {
                "strength": 6,
                "physique": 4,
                "agility": 7,
                "endurance": 4,
                "intelligence": 0,
                "initiative": 5,
                "luck": 5
            },
            "resistance": {
                "stabbing": 0,
                "cutting": 0,
                "crushing": 0,
                "fire": 0,
                "cold": 0,
                "lighting": 0,
                "poison": 0,
                "exhaustion": 0,
                "manaDrain": 0,
                "bleeding": 0,
                "fear": 0,
                "curse": 0,
                "madness": 0
            }
        },
        "slots": {
            "body": 1,
            "weapon": 1
        },
        "inventory": {
            "descriptor": [
                {
                    "code": "teeth-01",
                    "equipped": true
                }
            ]
        }
    },
    {
        "name": "Green Slime",
        "code": "slime-01",
        "stats": {
            "progress": {
                "level": 2,
                "experience": 30
            },
            "baseAttributes": {
                "health": 50,
                "stamina": 50
            },
            "attributes": {
                "strength": 8,
                "physique": 5,
                "agility": 5,
                "endurance": 5,
                "intelligence": 0,
                "initiative": 3,
                "luck": 5
            },
            "resistance": {
                "stabbing": 0,
                "cutting": 0,
                "crushing": 0,
                "fire": 0,
                "cold": 0,
                "lighting": 0,
                "poison": 100,
                "exhaustion": 0,
                "manaDrain": 0,
                "bleeding": 0,
                "fear": 0,
                "curse": 0,
                "madness": 0
            }
        },
        "slots": {
            "body": 1,
            "weapon": 1
        },
        "inventory": {
            "descriptor": [
                {
                    "code": "teeth-01",
                    "equipped": true
                }
            ]
        }
    },
    {
        "name": "Slow Green Slime",
        "code": "slime-02",
        "stats": {
            "progress": {
                "level": 2,
                "experience": 35
            },
            "baseAttributes": {
                "health": 60,
                "stamina": 40
            },
            "attributes": {
                "strength": 9,
                "physique": 5,
                "agility": 3,
                "endurance": 5,
                "intelligence": 0,
                "initiative": 1,
                "luck": 5
            },
            "resistance": {
                "stabbing": 0,
                "cutting": 0,
                "crushing": 0,
                "fire": 0,
                "cold": 0,
                "lighting": 0,
                "poison": 100,
                "exhaustion": 0,
                "manaDrain": 0,
                "bleeding": 0,
                "fear": 0,
                "curse": 0,
                "madness": 0
            }
        },
        "slots": {
            "body": 1,
            "weapon": 1
        },
        "inventory": {
            "descriptor": [
                {
                    "code": "teeth-01",
                    "equipped": true
                }
            ]
        }
    },
    {
        "name": "Cacodemon Green",
        "code": "cacodemon-01",
        "stats": {
            "progress": {
                "level": 2,
                "experience": 100
            },
            "baseAttributes": {
                "health": 100,
                "stamina": 100,
                "mana": 100
            },
            "attributes": {
                "strength": 10,
                "physique": 5,
                "agility": 5,
                "endurance": 5,
                "intelligence": 15,
                "initiative": 5,
                "luck": 5
            },
            "resistance": {
                "stabbing": 5,
                "cutting": 5,
                "crushing": 5,
                "fire": 0,
                "cold": 0,
                "lighting": 0,
                "poison": 100,
                "exhaustion": 5,
                "manaDrain": 5,
                "bleeding": 5,
                "fear": 100,
                "curse": 100,
                "madness": 100
            }
        },
        "slots": {
            "body": 1,
            "weapon": 1
        },
        "inventory": {
            "descriptor": [
                {
                    "code": "teeth-01"
                },
                {
                    "code": "sight-01",
                    "equipped": true
                },
                {
                    "code": "poison-charge-01",
                    "quantity": 5,
                    "equipped": true
                }
            ]
        }
    },
    {
        "name": "Cacodemon Blue",
        "code": "cacodemon-02",
        "stats": {
            "progress": {
                "level": 2,
                "experience": 120
            },
            "baseAttributes": {
                "health": 120,
                "stamina": 100,
                "mana": 100
            },
            "attributes": {
                "strength": 8,
                "physique": 5,
                "agility": 3,
                "endurance": 6,
                "intelligence": 18,
                "initiative": 5,
                "luck": 5
            },
            "resistance": {
                "stabbing": 5,
                "cutting": 5,
                "crushing": 5,
                "fire": 0,
                "cold": 100,
                "lighting": 0,
                "poison": 0,
                "exhaustion": 5,
                "manaDrain": 5,
                "bleeding": 5,
                "fear": 100,
                "curse": 100,
                "madness": 100
            }
        },
        "slots": {
            "body": 1,
            "weapon": 1
        },
        "inventory": {
            "descriptor": [
                {
                    "code": "teeth-01"
                },
                {
                    "code": "sight-01",
                    "equipped": true
                },
                {
                    "code": "cold-charge-01",
                    "quantity": 5,
                    "equipped": true
                }
            ]
        }
    },
    {
        "name": "Cacodemon Yellow",
        "code": "cacodemon-03",
        "stats": {
            "progress": {
                "level": 2,
                "experience": 120
            },
            "baseAttributes": {
                "health": 90,
                "stamina": 100,
                "mana": 100
            },
            "attributes": {
                "strength": 10,
                "physique": 5,
                "agility": 3,
                "endurance": 6,
                "intelligence": 15,
                "initiative": 5,
                "luck": 5
            },
            "resistance": {
                "stabbing": 5,
                "cutting": 5,
                "crushing": 5,
                "fire": 100,
                "cold": 0,
                "lighting": 0,
                "poison": 0,
                "exhaustion": 5,
                "manaDrain": 5,
                "bleeding": 5,
                "fear": 100,
                "curse": 100,
                "madness": 100
            }
        },
        "slots": {
            "body": 1,
            "weapon": 1
        },
        "inventory": {
            "descriptor": [
                {
                    "code": "teeth-01"
                },
                {
                    "code": "sight-01",
                    "equipped": true
                },
                {
                    "code": "fire-charge-01",
                    "quantity": 5,
                    "equipped": true
                }
            ]
        }
    },
    {
        "name": "Rat",
        "code": "rat-01",
        "stats": {
            "progress": {
                "level": 2,
                "experience": 40
            },
            "baseAttributes": {
                "health": 75,
                "stamina": 75
            },
            "attributes": {
                "strength": 12,
                "physique": 5,
                "agility": 5,
                "endurance": 5,
                "intelligence": 0,
                "initiative": 5,
                "luck": 5
            },
            "resistance": {
                "stabbing": 5,
                "cutting": 5,
                "crushing": 5,
                "fire": 0,
                "cold": 0,
                "lighting": 0,
                "poison": 0,
                "exhaustion": 0,
                "manaDrain": 0,
                "bleeding": 0,
                "fear": 0,
                "curse": 0,
                "madness": 0
            }
        },
        "slots": {
            "head": 1,
            "neck": 1,
            "body": 1,
            "hand": 2,
            "leg": 2,
            "weapon": 2
        },
        "inventory": {
            "descriptor": [
                {
                    "code": "fist-01",
                    "equipped": true
                }
            ]
        }
    },
    {
        "name": "Ghost",
        "code": "ghost-01",
        "stats": {
            "progress": {
                "level": 2,
                "experience": 45
            },
            "baseAttributes": {
                "health": 50,
                "stamina": 75
            },
            "attributes": {
                "strength": 12,
                "physique": 5,
                "agility": 10,
                "endurance": 5,
                "intelligence": 0,
                "initiative": 5,
                "luck": 5
            },
            "resistance": {
                "stabbing": 0,
                "cutting": 0,
                "crushing": 100,
                "fire": 100,
                "cold": 100,
                "lighting": 0,
                "poison": 100,
                "exhaustion": 100,
                "manaDrain": 0,
                "bleeding": 100,
                "fear": 0,
                "curse": 0,
                "madness": 0
            }
        },
        "slots": {
            "body": 1,
            "weapon": 1
        },
        "inventory": {
            "descriptor": [
                {
                    "code": "teeth-01",
                    "equipped": true
                }
            ]
        }
    },
    {
        "name": "Death",
        "code": "death-01",
        "stats": {
            "progress": {
                "level": 2,
                "experience": 100
            },
            "baseAttributes": {
                "health": 150,
                "stamina": 150
            },
            "attributes": {
                "strength": 15,
                "physique": 15,
                "agility": 15,
                "endurance": 30,
                "intelligence": 0,
                "initiative": 15,
                "luck": 5
            },
            "resistance": {
                "stabbing": 5,
                "cutting": 5,
                "crushing": 5,
                "fire": 0,
                "cold": 0,
                "lighting": 0,
                "poison": 15,
                "exhaustion": 10,
                "manaDrain": 0,
                "bleeding": 100,
                "fear": 100,
                "curse": 100,
                "madness": 100
            }
        },
        "slots": {
            "head": 1,
            "neck": 1,
            "body": 1,
            "hand": 2,
            "leg": 2,
            "weapon": 2
        },
        "inventory": {
            "descriptor": [
                {
                    "code": "fist-01"
                },
                {
                    "code": "scythe-01",
                    "equipped": true
                }
            ]
        }
    },
    {
        "name": "Skeleton",
        "code": "skeleton-01",
        "stats": {
            "progress": {
                "level": 2,
                "experience": 80
            },
            "baseAttributes": {
                "health": 75,
                "stamina": 300
            },
            "attributes": {
                "strength": 15,
                "physique": 15,
                "agility": 0,
                "endurance": 15,
                "intelligence": 0,
                "initiative": 0,
                "luck": 0
            },
            "resistance": {
                "stabbing": 15,
                "cutting": 15,
                "crushing": 0,
                "fire": 0,
                "cold": 0,
                "lighting": 0,
                "poison": 0,
                "exhaustion": 0,
                "manaDrain": 0,
                "bleeding": 100,
                "fear": 100,
                "curse": 0,
                "madness": 100
            }
        },
        "slots": {
            "head": 1,
            "neck": 1,
            "body": 1,
            "hand": 2,
            "leg": 2,
            "weapon": 2
        },
        "inventory": {
            "descriptor": [
                {
                    "code": "fist-01"
                },
                {
                    "code": "sword-01",
                    "equipped": true
                }
            ]
        }
    },
    {
        "name": "Dragon",
        "code": "dragon-01",
        "stats": {
            "progress": {
                "level": 2,
                "experience": 80
            },
            "baseAttributes": {
                "health": 500,
                "stamina": 200,
                "mana": 200
            },
            "attributes": {
                "strength": 35,
                "physique": 25,
                "agility": 10,
                "endurance": 25,
                "intelligence": 25,
                "initiative": 10,
                "luck": 10
            },
            "resistance": {
                "stabbing": 25,
                "cutting": 25,
                "crushing": 25,
                "fire": 25,
                "cold": 25,
                "lighting": 25,
                "poison": 0,
                "exhaustion": 15,
                "manaDrain": 25,
                "bleeding": 15,
                "fear": 100,
                "curse": 100,
                "madness": 100
            }
        },
        "slots": {
            "head": 1,
            "neck": 1,
            "body": 1,
            "wing": 2,
            "leg": 2,
            "weapon": 1
        },
        "inventory": {
            "descriptor": [
                {
                    "code": "teeth-01"
                },
                {
                    "code": "throat-01",
                    "equipped": true
                },
                {
                    "code": "fire-charge-02",
                    "quantity": 50,
                    "equipped": true
                }
            ]
        }
    }
]